CONTRIBUTING.rst
LICENSE
MANIFEST.in
README.md
setup.cfg
setup.py
docs/Makefile
docs/authors.rst
docs/conf.py
docs/contributing.rst
docs/history.rst
docs/index.rst
docs/installation.rst
docs/make.bat
docs/readme.rst
docs/usage.rst
tests/__init__.py
tests/test_vcf-annotate-polyphen.py
vap/__init__.py
vap/annotator.py
vap/cli.py
vcf_annotate_polyphen.egg-info/PKG-INFO
vcf_annotate_polyphen.egg-info/SOURCES.txt
vcf_annotate_polyphen.egg-info/dependency_links.txt
vcf_annotate_polyphen.egg-info/entry_points.txt
vcf_annotate_polyphen.egg-info/not-zip-safe
vcf_annotate_polyphen.egg-info/requires.txt
vcf_annotate_polyphen.egg-info/top_level.txt