Metadata-Version: 1.1
Name: vcf-annotate-polyphen
Version: 0.1.2
Summary: a tool to annotate human VCF files with PolyPhen2 effect measures
Home-page: https://github.com/hammerlab/vcf-annotate-polyphen
Author: B. Arman Aksoy
Author-email: arman@aksoy.org
License: http://www.apache.org/licenses/LICENSE-2.0.html
Keywords: vcf-annotate-polyphen
Platform: UNKNOWN
Classifier: Development Status :: 2 - Pre-Alpha
Classifier: Intended Audience :: Developers
Classifier: License :: OSI Approved :: ISC License (ISCL)
Classifier: Natural Language :: English
Classifier: Programming Language :: Python :: 2
Classifier: Programming Language :: Python :: 2.6
Classifier: Programming Language :: Python :: 2.7
Classifier: Programming Language :: Python :: 3
Classifier: Programming Language :: Python :: 3.3
Classifier: Programming Language :: Python :: 3.4
Classifier: Programming Language :: Python :: 3.5
